MANIFEST.in
README.md
README.txt
setup.py
OASYS1_SHADOWFOUR.egg-info/PKG-INFO
OASYS1_SHADOWFOUR.egg-info/SOURCES.txt
OASYS1_SHADOWFOUR.egg-info/dependency_links.txt
OASYS1_SHADOWFOUR.egg-info/entry_points.txt
OASYS1_SHADOWFOUR.egg-info/namespace_packages.txt
OASYS1_SHADOWFOUR.egg-info/not-zip-safe
OASYS1_SHADOWFOUR.egg-info/requires.txt
OASYS1_SHADOWFOUR.egg-info/top_level.txt
orangecontrib/__init__.py
orangecontrib/shadow4/__init__.py
orangecontrib/shadow4/util/__init__.py
orangecontrib/shadow4/util/python_script.py
orangecontrib/shadow4/util/shadow_objects.py
orangecontrib/shadow4/util/shadow_util.py
orangecontrib/shadow4/widgets/__init__.py
orangecontrib/shadow4/widgets/gui/__init__.py
orangecontrib/shadow4/widgets/gui/ow_automatic_element.py
orangecontrib/shadow4/widgets/gui/ow_electron_beam.py
orangecontrib/shadow4/widgets/gui/ow_generic_element.py
orangecontrib/shadow4/widgets/gui/ow_light_source_old.py
orangecontrib/shadow4/widgets/gui/plots.py
orangecontrib/shadow4/widgets/sources/__init__.py
orangecontrib/shadow4/widgets/sources/ow_wiggler.py
orangecontrib/shadow4/widgets/sources/icons/bending_magnet.png
orangecontrib/shadow4/widgets/sources/icons/geometrical.png
orangecontrib/shadow4/widgets/sources/icons/source.png
orangecontrib/shadow4/widgets/sources/icons/ugaussian.png
orangecontrib/shadow4/widgets/sources/icons/undulator.png
orangecontrib/shadow4/widgets/sources/icons/wiggler.png
orangecontrib/shadow4/widgets/tools/__init__.py
orangecontrib/shadow4/widgets/tools/icons/beam_file_reader.png
orangecontrib/shadow4/widgets/tools/icons/beam_file_writer.png
orangecontrib/shadow4/widgets/tools/icons/image_converter.png
orangecontrib/shadow4/widgets/tools/icons/merge.png
orangecontrib/shadow4/widgets/tools/icons/to_wofry_wavefront_2d.png
orangecontrib/shadow4/widgets/tools/icons/utility.png