Metadata-Version: 1.1
Name: OASYS1-SHADOWFOUR
Version: 0.0.3
Summary: oasys-shadow4: Oasys widgets for shadow4
Home-page: https://github.com/srio/OASYS-SHADOW4
Author: M. Sanchez del Rio
Author-email: srio@lbl.gov
License: MIT
Download-URL: https://github.com/srio/OASYS-SHADOW4
Keywords: application,Oasys,Orange,shadow4
Platform: UNKNOWN
Classifier: Development Status :: 4 - Beta
Classifier: Environment :: X11 Applications :: Qt
Classifier: Environment :: Console
Classifier: Environment :: Plugins
Classifier: Programming Language :: Cython
Classifier: Programming Language :: Python
Classifier: Programming Language :: Python :: 3
Classifier: Intended Audience :: Science/Research
